tests/__init__.py
tests/username_type_test.py
tests/func-tests/__init__.py
tests/func-tests/steps/__init__.py
tests/func-tests/steps/steps.py
tests/unit-tests/__init__.py
tests/unit-tests/bot_type_test.py
tests/unit-tests/primitives_test.py
tests/unit-tests/role_type_test.py
tests/unit-tests/userid_type_test.py
tests/unit-tests/username_type_test.py
tests/unit-tests/welcome_config_test.py
walle/__init__.py
walle/bot/__init__.py
walle/bot/welcome_bot.py
walle/bot/base/__init__.py
walle/bot/base/bot.py
walle/configs/__init__.py
walle/configs/welcome_config.py
walle/configs/base/__init__.py
walle/configs/base/config.py
walle/configs/base/constants.py
walle/core/__init__.py
walle/core/bot_type.py
walle/core/role_type.py
walle/core/userid_type.py
walle/core/username_type.py
walle/core/base/__init__.py
walle/core/base/primitives.py
discord_walle-0.2.12.dist-info/METADATA
discord_walle-0.2.12.dist-info/WHEEL
discord_walle-0.2.12.dist-info/top_level.txt
discord_walle-0.2.12.dist-info/RECORD
