Metadata-Version: 2.1
Name: discord-walle
Version: 0.2.12
Summary: General Discord Utility Bot
Home-page: UNKNOWN
Author: ['Jon Perry', 'Josh Oliveira']
License: Unlicense
Platform: UNKNOWN
Requires-Python: ~=3.8
Requires-Dist: discord (==2.1.0)
Requires-Dist: black (==22.10.0)
Requires-Dist: flake8 (==6.0.0)
Requires-Dist: pre-commit (==2.20.0)
